DatastreamDSWS_Test/DS_Requests.py
DatastreamDSWS_Test/DS_Response.py
DatastreamDSWS_Test/__init__.py
DatastreamDSWS_Test-0.0.7.dist-info/METADATA
DatastreamDSWS_Test-0.0.7.dist-info/WHEEL
DatastreamDSWS_Test-0.0.7.dist-info/top_level.txt
DatastreamDSWS_Test-0.0.7.dist-info/RECORD
